gpty/__init__.py
gpty/gpty/__init__.py
gpty/gpty/gpty.py
gpty/gpty/prompt_templates.py
gpty/main.py
gpty/utility/__init__.py
gpty/utility/utility.py
gpty-0.1.0.dist-info/LICENSE
gpty-0.1.0.dist-info/METADATA
gpty-0.1.0.dist-info/WHEEL
gpty-0.1.0.dist-info/entry_points.txt
gpty-0.1.0.dist-info/RECORD
