Metadata-Version: 2.1
Name: gpty
Version: 0.1.0
Summary: A CLI tool for ChatGPT
Author: Ismet Handzic
Author-email: ismet.handzic@gmail.com
Requires-Python: >=3.10,<4.0
Classifier: Programming Language :: Python :: 3
Classifier: Programming Language :: Python :: 3.10
Classifier: Programming Language :: Python :: 3.11
Requires-Dist: PyYAML (>=6.0,<7.0)
Requires-Dist: click (>=8.1.3,<9.0.0)
Requires-Dist: coloredlogs (>=15.0.1,<16.0.0)
Requires-Dist: openai (>=0.27.7,<0.28.0)
Requires-Dist: requests (>=2.31.0,<3.0.0)
Requires-Dist: toml (>=0.10.2,<0.11.0)
Requires-Dist: twine (>=4.0.2,<5.0.0)
Requires-Dist: yaspin (>=2.3.0,<3.0.0)
